verifystream/__init__.py
verifystream/verify.py
VerifySteream-1.8.15.dist-info/METADATA
VerifySteream-1.8.15.dist-info/WHEEL
VerifySteream-1.8.15.dist-info/top_level.txt
VerifySteream-1.8.15.dist-info/RECORD
