Metadata-Version: 2.1
Name: VerifySteream
Version: 1.8.15
Summary: Streaming bytes data via networks
Home-page: UNKNOWN
Author: neon
Author-email: neon@webmail.com
License: UNKNOWN
Keywords: python,video,stream,video stream,camera stream,sockets
Platform: UNKNOWN
Classifier: Development Status :: 1 - Planning
Classifier: Intended Audience :: Developers
Classifier: Programming Language :: Python :: 3
Classifier: Operating System :: Unix
Classifier: Operating System :: MacOS :: MacOS X
Classifier: Operating System :: Microsoft :: Windows
Requires-Dist: requests
